README.md
setup.py
reconto/__init__.py
reconto.egg-info/PKG-INFO
reconto.egg-info/SOURCES.txt
reconto.egg-info/dependency_links.txt
reconto.egg-info/entry_points.txt
reconto.egg-info/not-zip-safe
reconto.egg-info/requires.txt
reconto.egg-info/top_level.txt