Metadata-Version: 2.1
Name: reconto
Version: 0.0.1
Summary: REsearch COmpendium memeNTO
Home-page: https://github.com/dicaso/reconto
Author: Christophe Van Neste
Author-email: christophe.vanneste@ugent.be
License: GNU GENERAL PUBLIC LICENSE
Platform: UNKNOWN
Provides-Extra: dev
